nested_pandas/__init__.py
nested_pandas/_version.py
nested_pandas/py.typed
nested_pandas/datasets/__init__.py
nested_pandas/datasets/generation.py
nested_pandas/nestedframe/__init__.py
nested_pandas/nestedframe/core.py
nested_pandas/nestedframe/expr.py
nested_pandas/nestedframe/io.py
nested_pandas/series/__init__.py
nested_pandas/series/accessor.py
nested_pandas/series/dtype.py
nested_pandas/series/ext_array.py
nested_pandas/series/nestedseries.py
nested_pandas/series/packer.py
nested_pandas/series/utils.py
nested_pandas/series/_storage/__init__.py
nested_pandas/series/_storage/list_struct_storage.py
nested_pandas/series/_storage/struct_list_storage.py
nested_pandas/series/_storage/table_storage.py
nested_pandas/utils/__init__.py
nested_pandas/utils/utils.py
nested_pandas-0.6.7.dist-info/licenses/LICENSE
nested_pandas-0.6.7.dist-info/METADATA
nested_pandas-0.6.7.dist-info/WHEEL
nested_pandas-0.6.7.dist-info/top_level.txt
nested_pandas-0.6.7.dist-info/RECORD
