Metadata-Version: 2.4
Name: nested-pandas
Version: 0.6.7
Summary: An extension of pandas for efficient representation of nested associated datasets.
Author-email: LINCC Frameworks <brantd@uw.edu>
License-Expression: MIT
Project-URL: Source Code, https://github.com/lincc-frameworks/nested-pandas
Classifier: Development Status :: 4 - Beta
Classifier: Intended Audience :: Developers
Classifier: Intended Audience :: Science/Research
Classifier: Operating System :: OS Independent
Classifier: Programming Language :: Python
Requires-Python: >=3.10
License-File: LICENSE
Requires-Dist: numpy>=2
Requires-Dist: pandas<2.4,>=2.2.3
Requires-Dist: pyarrow>=16
Requires-Dist: Deprecated>=1.2.0
Requires-Dist: wrapt>=1.12.1
Requires-Dist: fsspec<2025.12.0,>=2025.7.0
Requires-Dist: universal_pathlib>=0.3.1
Provides-Extra: dev
Requires-Dist: asv[virtualenv]==0.6.5; extra == "dev"
Requires-Dist: jupyter; extra == "dev"
Requires-Dist: mypy; extra == "dev"
Requires-Dist: pre-commit; extra == "dev"
Requires-Dist: pytest; extra == "dev"
Requires-Dist: pytest-cov; extra == "dev"
Requires-Dist: ruff; extra == "dev"
Requires-Dist: aiohttp; extra == "dev"
Requires-Dist: requests; extra == "dev"
Requires-Dist: s3fs; extra == "dev"
Requires-Dist: types-Deprecated; extra == "dev"
Dynamic: license-file
